setup.py
pyframe/__init__.py
pyframe/__main__.py
pyframe/classes.py
pyframe/constants.py
pyframe/exception.py
pyframe/functions.py
pyframe/examples/__init__.py
pygame_frame.egg-info/PKG-INFO
pygame_frame.egg-info/SOURCES.txt
pygame_frame.egg-info/dependency_links.txt
pygame_frame.egg-info/requires.txt
pygame_frame.egg-info/top_level.txt