Metadata-Version: 1.1
Name: pygame-frame
Version: 0.0.6
Summary: A lib to simplify the use of pygame
Home-page: https://github.com/paulnbrd/PyFrame/
Author: PØL1
Author-email: UNKNOWN
License: UNKNOWN
Platform: UNKNOWN
Classifier: Programming Language :: Python
Classifier: Development Status :: 1 - Planning
Classifier: Natural Language :: French
Classifier: Operating System :: OS Independent
Classifier: Programming Language :: Python :: 3.9
